mosaic/__init__.py
mosaic/__version__.py
mosaic/actor.py
mosaic/animation/__init__.py
mosaic/animation/_utils.py
mosaic/animation/animations.py
mosaic/animation/compose.py
mosaic/animation/settings.py
mosaic/animation/timeline.py
mosaic/container.py
mosaic/data/checkbox-checkmark.svg
mosaic/data/dock-close.svg
mosaic/data/dock-float.svg
mosaic/data/logo.png
mosaic/data/mosaic.icns
mosaic/data.py
mosaic/dialogs/__init__.py
mosaic/dialogs/appsettings.py
mosaic/dialogs/backmapping.py
mosaic/dialogs/cropping.py
mosaic/dialogs/equilibration.py
mosaic/dialogs/export.py
mosaic/dialogs/file_dialog.py
mosaic/dialogs/histogram.py
mosaic/dialogs/hmff.py
mosaic/dialogs/import_data.py
mosaic/dialogs/matching.py
mosaic/dialogs/progress.py
mosaic/dialogs/properties.py
mosaic/dialogs/property_analysis.py
mosaic/dialogs/tilt_control.py
mosaic/dialogs/update.py
mosaic/formats/__init__.py
mosaic/formats/_utils.py
mosaic/formats/parser.py
mosaic/formats/reader.py
mosaic/formats/writer.py
mosaic/geometry.py
mosaic/gui.py
mosaic/icons.py
mosaic/interactor.py
mosaic/meshing/__init__.py
mosaic/meshing/coarse_graining.py
mosaic/meshing/hmff.py
mosaic/meshing/repair.py
mosaic/meshing/utils.py
mosaic/meshing/volume.py
mosaic/operations.py
mosaic/parallel.py
mosaic/parametrization.py
mosaic/pipeline/__init__.py
mosaic/pipeline/_utils.py
mosaic/pipeline/dialog.py
mosaic/pipeline/executor.py
mosaic/pipeline/operations.py
mosaic/pipeline/widgets.py
mosaic/properties.py
mosaic/scripts/__init__.py
mosaic/scripts/app.py
mosaic/scripts/pipeline.py
mosaic/segmentation/__init__.py
mosaic/segmentation/membrain.py
mosaic/settings.py
mosaic/styles.py
mosaic/stylesheets.py
mosaic/tabs/__init__.py
mosaic/tabs/development.py
mosaic/tabs/intelligence.py
mosaic/tabs/model.py
mosaic/tabs/segmentation.py
mosaic/utils.py
mosaic/widgets/__init__.py
mosaic/widgets/colors.py
mosaic/widgets/container_list.py
mosaic/widgets/dialog_footer.py
mosaic/widgets/dock.py
mosaic/widgets/path_selector.py
mosaic_gui-1.1.1.dist-info/LICENSE
mosaic_gui-1.1.1.dist-info/METADATA
mosaic_gui-1.1.1.dist-info/WHEEL
mosaic_gui-1.1.1.dist-info/entry_points.txt
mosaic_gui-1.1.1.dist-info/RECORD
