Metadata-Version: 2.3
Name: mosaic-gui
Version: 1.1.1
Summary: mosaic
License: GPL-2.0-only
Author: Valentin Maurer
Author-email: valentin.maurer@embl-hamburg.de
Requires-Python: >=3.11,<4.0
Classifier: License :: OSI Approved :: GNU General Public License v2 (GPLv2)
Classifier: Programming Language :: Python :: 3
Classifier: Programming Language :: Python :: 3.11
Classifier: Programming Language :: Python :: 3.12
Classifier: Programming Language :: Python :: 3.13
Requires-Dist: Pillow
Requires-Dist: PyQt6 (==6.7.1)
Requires-Dist: imageio
Requires-Dist: imageio-ffmpeg
Requires-Dist: importlib_resources
Requires-Dist: leidenalg (>=0.9)
Requires-Dist: libigl (==2.5.1)
Requires-Dist: matplotlib
Requires-Dist: numpy (<2.0)
Requires-Dist: open3d (>=0.18.0)
Requires-Dist: packaging
Requires-Dist: pyfqmr (>=0.3.0)
Requires-Dist: pymeshlab (>=2023.12)
Requires-Dist: pyqtgraph (>=0.13.3)
Requires-Dist: pytme (>=0.3.3)
Requires-Dist: qtawesome
Requires-Dist: scipy (>=1.14.0)
Requires-Dist: tqdm (>=4.67.1)
Requires-Dist: vtk (>=9.3.1)
Requires-Dist: zmesh (>=1.8.0)
Project-URL: Homepage, https://github.com/KosinskiLab/mosaic
Project-URL: Repository, https://github.com/KosinskiLab/mosaic
